mime/rapunzel.desktop
mime/rapunzel.svg
opensesame_extensions/ide/__init__.py
opensesame_extensions/ide/data_viewer/__init__.py
opensesame_extensions/ide/data_viewer/data_viewer.py
opensesame_extensions/ide/data_viewer/data_viewer_file_handlers/__init__.py
opensesame_extensions/ide/data_viewer/data_viewer_file_handlers/_base_file_handler.py
opensesame_extensions/ide/data_viewer/data_viewer_file_handlers/_ir_file_handler.py
opensesame_extensions/ide/data_viewer/data_viewer_file_handlers/_python_file_handler.py
opensesame_extensions/ide/data_viewer/data_viewer_inspectors/__init__.py
opensesame_extensions/ide/data_viewer/data_viewer_inspectors/inspect_DataFrame.py
opensesame_extensions/ide/data_viewer/data_viewer_inspectors/inspect_DataMatrix.py
opensesame_extensions/ide/data_viewer/data_viewer_inspectors/inspect_JpegImageFile.py
opensesame_extensions/ide/data_viewer/data_viewer_inspectors/inspect_Nifti1Image.py
opensesame_extensions/ide/data_viewer/data_viewer_inspectors/inspect_Nifti2Image.py
opensesame_extensions/ide/data_viewer/data_viewer_inspectors/inspect_PngImageFile.py
opensesame_extensions/ide/data_viewer/data_viewer_inspectors/inspect_dict.py
opensesame_extensions/ide/data_viewer/data_viewer_inspectors/inspect_list.py
opensesame_extensions/ide/data_viewer/data_viewer_inspectors/inspect_ndarray.py
opensesame_extensions/ide/data_viewer/data_viewer_inspectors/inspect_set.py
opensesame_extensions/ide/data_viewer/data_viewer_inspectors/inspect_str.py
opensesame_extensions/ide/data_viewer/data_viewer_inspectors/inspect_tuple.py
opensesame_extensions/ide/data_viewer/datadockwidget.py
opensesame_extensions/ide/find_in_files/__init__.py
opensesame_extensions/ide/find_in_files/find_in_files.py
opensesame_extensions/ide/find_in_files/find_in_files.ui
opensesame_extensions/ide/git_gui/__init__.py
opensesame_extensions/ide/git_gui/git_gui.py
opensesame_extensions/ide/ide_launcher/__init__.py
opensesame_extensions/ide/ide_launcher/ide_launcher.py
rapunzel-1.0.0.dist-info/METADATA
rapunzel-1.0.0.dist-info/WHEEL
rapunzel-1.0.0.dist-info/entry_points.txt
rapunzel-1.0.0.dist-info/RECORD
