Metadata-Version: 2.1
Name: rapunzel
Version: 1.0.0
Summary: A modern code editor focused on numerical computing with Python and R
Home-page: https://rapunzel.cogsci.nl
Author: Sebastiaan Mathôt
Author-email: s.mathot@cogsci.nl
Requires-Python: >=3.7,<4.0
Classifier: Programming Language :: Python :: 3
Classifier: Programming Language :: Python :: 3.7
Classifier: Programming Language :: Python :: 3.8
Classifier: Programming Language :: Python :: 3.9
Classifier: Programming Language :: Python :: 3.10
Classifier: Programming Language :: Python :: 3.11
Requires-Dist: esprima
Requires-Dist: opensesame-core (>=4.0.0a1)
Requires-Dist: psutil
Requires-Dist: pyspellchecker
Requires-Dist: python-levenshtein
Requires-Dist: qtconsole
Project-URL: Repository, https://github.com/open-cogsci/rapunzel/
